sharePlayer
