Metadata-Version: 1.1
Name: sharePlayer
Version: 0.1.9
Summary: Script to synchronize video playback over a network
Home-page: https://github.com/owlz/sharePlayer
Author: Michael Bann
Author-email: self@bannsecurity.com
License: MIT
Keywords: video playback
Platform: UNKNOWN
Classifier: Development Status :: 5 - Production/Stable
Classifier: Intended Audience :: End Users/Desktop
Classifier: License :: OSI Approved :: MIT License
Classifier: Programming Language :: Python :: 3
Classifier: Operating System :: POSIX :: Linux
Classifier: Environment :: Console
